atro_rsync/__init__.py
atro_rsync/helpers.py
atro_rsync-0.2.0.dist-info/METADATA
atro_rsync-0.2.0.dist-info/WHEEL
atro_rsync-0.2.0.dist-info/RECORD
