Metadata-Version: 2.1
Name: atro-rsync
Version: 0.2.0
Summary: Rsync wrapper.
Author: atropos
Author-email: sv7n@pm.me
Requires-Python: >=3.11,<4.0
Classifier: Programming Language :: Python :: 3
Classifier: Programming Language :: Python :: 3.11
